Sidra/FAST.py
Sidra/__init__.py
Sidra-1.1.0.data/scripts/Sidra
Sidra-1.1.0.dist-info/LICENSE
Sidra-1.1.0.dist-info/METADATA
Sidra-1.1.0.dist-info/WHEEL
Sidra-1.1.0.dist-info/top_level.txt
Sidra-1.1.0.dist-info/RECORD
