Metadata-Version: 2.1
Name: Sidra
Version: 1.1.0
Summary: Sidra tool!
Home-page: https://github.com/SidtaELEzz
Author: SidraELEzz
License: UNKNOWN
Platform: UNKNOWN
Classifier: Programming Language :: Python :: 3
Classifier: License :: OSI Approved :: MIT License
Classifier: Operating System :: OS Independent
Requires-Python: >=3.6
License-File: LICENSE
